MANIFEST.in
mkdocs.yml
setup.py
docs/README.md
docs/deploy.md
docs/development.md
docs/release-note.md
docs/user-guide.md
src/routeviews_google_upload/__init__.py
src/routeviews_google_upload/__main__.py
src/routeviews_google_upload/client.py
src/routeviews_google_upload/echo_server.py
src/routeviews_google_upload/rv_pb2.py
src/routeviews_google_upload/rv_pb2_grpc.py
src/routeviews_google_upload.egg-info/PKG-INFO
src/routeviews_google_upload.egg-info/SOURCES.txt
src/routeviews_google_upload.egg-info/dependency_links.txt
src/routeviews_google_upload.egg-info/entry_points.txt
src/routeviews_google_upload.egg-info/requires.txt
src/routeviews_google_upload.egg-info/top_level.txt