Metadata-Version: 2.1
Name: routeviews-google-upload
Version: 0.2.0
Summary: CLI tool for uploading RouteViews files to Google.
Home-page: https://github.com/routeviews/google-cloud-storage
Author: University of Oregon
Author-email: rleonar7@uoregon.edu
License: apache-2.0
Keywords: RouteViews,Google,Cloud,Storage,Backup,Archive
Platform: UNKNOWN
Classifier: Development Status :: 3 - Alpha
Classifier: Intended Audience :: Developers
Classifier: Topic :: Software Development
Classifier: License :: OSI Approved :: Apache Software License
Classifier: Programming Language :: Python :: 3.6
Classifier: Programming Language :: Python :: 3.7
Classifier: Programming Language :: Python :: 3.8
